pytest_argus_server/__init__.py
pytest_argus_server/plugin.py
pytest_argus_server/docker/Dockerfile
pytest_argus_server/docker/ci_settings.py
pytest_argus_server/docker/docker-compose.yml
pytest_argus_server-0.2.0.dist-info/licenses/LICENSE
pytest_argus_server-0.2.0.dist-info/METADATA
pytest_argus_server-0.2.0.dist-info/WHEEL
pytest_argus_server-0.2.0.dist-info/entry_points.txt
pytest_argus_server-0.2.0.dist-info/top_level.txt
pytest_argus_server-0.2.0.dist-info/RECORD
