Metadata-Version: 2.4
Name: pytest-argus-server
Version: 0.2.0
Summary: A plugin that provides a running Argus API server for tests
Author-email: Sikt - Kunnskapssektorens Tjenesteleverandør <kontakt@sikt.no>
Maintainer-email: Morten Brekkevold <morten.brekkevold@sikt.no>
License: 
Project-URL: Repository, https://github.com/Uninett/pytest-argus-server
Platform: any
Classifier: Framework :: Pytest
Classifier: Development Status :: 4 - Beta
Classifier: Intended Audience :: Developers
Classifier: Topic :: Software Development :: Testing
Classifier: Operating System :: OS Independent
Classifier: Programming Language :: Python
Classifier: Programming Language :: Python :: 3.9
Classifier: Programming Language :: Python :: 3.10
Classifier: Programming Language :: Python :: 3.11
Classifier: Programming Language :: Python :: 3.12
Classifier: Programming Language :: Python :: 3 :: Only
Classifier: Programming Language :: Python :: Implementation :: CPython
Classifier: License :: OSI Approved :: Apache Software License
Requires-Python: >=3.9
License-File: LICENSE
Requires-Dist: pytest>=6.2.0
Requires-Dist: pytest-docker-compose-v2==0.1.1
Requires-Dist: requests
Dynamic: license-file
